Workbook

Sheet Start Here
A1: CLIENT FINANCIAL POSITION & FACT FIND
A5: WHITE-LABEL WORKBOOK · START HERE
A6: HOW THIS WORKBOOK FITS TOGETHER Complete the tabs left to right. 'White Label Setup' carries your organisation's name, contact details and brand colours; every other tab reads from it. 'Client Fact Find' and 'Living Expenses' are the data-entry forms. 'Client Form Output' is the print-ready summary — it is entirely formula-driven, so never type into it.
A10: TAB GUIDE What each sheet is for
B11: Tab | C11: Purpose | D11: Who completes it | E11: Print? | F11: Notes
B12: White Label Setup | C12: Organisation branding and document settings | D12: Partner administrator | E12: No | F12: Complete once per organisation.
B13: Client Fact Find | C13: Applicant details, employment, assets and liabilities | D13: Client, with adviser support | E13: Yes | F13: Yellow cells are inputs.
B14: Living Expenses | C14: Monthly household expenditure by category | D14: Client | E14: Yes | F14: Enter monthly figures; annual is calculated.
B15: Client Form Output | C15: Print-ready summary and client declaration | D15: Generated automatically | E15: Yes | F15: Formula-driven — do not overtype.
A17: COMPLETION CHECKLIST Before you issue or export
B18: ☐ Set the organisation name, contact details and brand colours on 'White Label Setup'.
B19: ☐ Replace the logo placeholder with the partner mark.
B20: ☐ Confirm the confidentiality label and disclaimer wording.
B21: ☐ Complete every applicant, employment, asset and liability row that applies.
B22: ☐ Enter monthly living expenses — leave inapplicable lines at zero.
B23: ☐ Review 'Client Form Output' for blank or negative figures.
B24: ☐ Have the client sign the declaration, then export to PDF.
A27: DATA HANDLING This workbook holds personal and financial information. Store it in a restricted-access location, share it only through an approved secure channel, and retain it for the period required by your privacy policy and compliance framework.

Sheet White Label Setup
A1: WHITE-LABEL CONFIGURATION
A5: ORGANISATION IDENTITY Shown on every tab and in the exported PDF
B6: Organisation Name | C6: NPC Services | E6: Document Title | F6: Client Financial Position & Fact Find
B7: Trading Name / Division | E7: Confidentiality Label | F7: CONFIDENTIAL
B8: Tagline | C8: YOUR TRUSTED PROPERTY & FINANCE PARTNER | E8: Prepared By
B9: Website | C9: www.yourorganisation.com.au | E9: Version | F9: 1.0
B10: Email | C10: info@yourorganisation.com.au | E10: Primary Colour (Hex) | F10: #251F18
B11: Phone | C11: (00) 0000 0000 | E11: Accent Colour (Hex) | F11: #D9A520
B12: Business Address | C12: Insert business address | E12: Logo Placeholder | F12: Replace this area with your logo
B13: ABN / ACN | E13: Disclaimer | F13: Insert licensing or credit-guide wording, or leave blank
A15: COLOUR FIELDS The hex values above are recorded for reference and are applied automatically when the Aurixa Finance Portal generates a branded export. To re-skin the workbook by hand, select a banner row and apply the same colour from Excel's fill picker — the semantic colours (green, amber, red) should stay as they are.
A19: IMPLEMENTATION NOTE This workbook is intentionally organisation-neutral. The Aurixa Systems Client Forms module can map each editable field to its database, apply the selected organisation's brand settings, and generate the downloadable 'Client Form Output' without displaying any external finance-partner branding.

Sheet Client Fact Find
A1: CLIENT FACT FIND
A3: ='White Label Setup'!C6&" | "&'White Label Setup'!F6&" | "&'White Label Setup'!F7
A5: PERSONAL DETAILS Applicant 1 (columns A–E) · Applicant 2 (columns F–J)
A6: Title | F6: Title
A7: First Name | F7: First Name
A8: Middle Name | F8: Middle Name
A9: Surname | F9: Surname
A10: Date of Birth | F10: Date of Birth
A11: Gender | F11: Gender
A12: Marital Status | F12: Marital Status
A13: Residency Status | F13: Residency Status
A14: Number of Dependants | F14: Number of Dependants
A15: Mobile | F15: Mobile
A16: Email | F16: Email
A18: ADDRESS HISTORY Include the previous address where the current one is under three years
A19: Current Address | F19: Current Address
A20: Living Situation | F20: Living Situation
A21: Date Moved In | F21: Date Moved In
A22: Previous Address | F22: Previous Address
A23: Previous Living Situation | F23: Previous Living Situation
A24: Previous Date Moved In | F24: Previous Date Moved In
A26: CURRENT EMPLOYMENT & INCOME Gross annual amounts
A27: Employment Type | F27: Employment Type
A28: Employer / Business | F28: Employer / Business
A29: Role / Position | F29: Role / Position
A30: Employer Address | F30: Employer Address
A31: Start Date | F31: Start Date
A32: Base Salary (Annual) | F32: Base Salary (Annual)
A33: Bonus | F33: Bonus
A34: Commission | F34: Commission
A35: Overtime | F35: Overtime
A36: Other Taxable Income | F36: Other Taxable Income
A38: ASSETS Include any loan secured against each asset
A39: Asset Type | B39: Description / Address | C39: Owner | D39: Current Value | E39: Rental / Other Income | F39: Financial Institution | G39: Loan Balance | H39: Monthly Repayment | I39: Interest Rate | J39: Maturity Date
A50: TOTAL ASSETS | D50: =SUM(D40:D49) | E50: =SUM(E40:E49) | G50: =SUM(G40:G49) | H50: =SUM(H40:H49)
A51: OTHER LIABILITIES Debts not already secured against an asset above
A52: Liability Type | B52: Lender | C52: Account / Description | D52: Owner | E52: Limit / Original Amount | F52: Current Balance | G52: Monthly Repayment | H52: Interest Rate | I52: Remaining Term | J52: Notes
A61: TOTAL OTHER LIABILITIES | E61: =SUM(E53:E60) | F61: =SUM(F53:F60) | G61: =SUM(G53:G60)
A63: COMPLETING THIS FORM Yellow cells are for you to complete; grey totals calculate themselves. Leave a row blank rather than entering zero if it does not apply. Where a loan is secured against an asset, record it on the asset row so it is not counted twice.

Sheet Living Expenses
A1: MONTHLY LIVING EXPENSES
A4: Category | B4: Expense Item | C4: Monthly Amount | D4: Annual (auto) | E4: Notes | G4: BY CATEGORY | H4: Monthly
A5: Childcare & Support | B5: Childcare | C5: 0 | D5: =C5*12 | G5: Childcare & Support | H5: =SUMIF($A$5:$A$54,G5,$C$5:$C$54)
A6: Childcare & Support | B6: Child Maintenance | C6: 0 | D6: =C6*12 | G6: Education | H6: =SUMIF($A$5:$A$54,G6,$C$5:$C$54)
A7: Education | B7: Public School Costs | C7: 0 | D7: =C7*12 | G7: Groceries | H7: =SUMIF($A$5:$A$54,G7,$C$5:$C$54)
A8: Education | B8: Private School Costs | C8: 0 | D8: =C8*12 | G8: Primary Residence | H8: =SUMIF($A$5:$A$54,G8,$C$5:$C$54)
A9: Education | B9: Higher Education / Vocational Training | C9: 0 | D9: =C9*12 | G9: Insurance | H9: =SUMIF($A$5:$A$54,G9,$C$5:$C$54)
A10: Groceries | B10: Groceries | C10: 0 | D10: =C10*12 | G10: Investment Property | H10: =SUMIF($A$5:$A$54,G10,$C$5:$C$54)
A11: Primary Residence | B11: Electricity & Gas | C11: 0 | D11: =C11*12 | G11: Secondary Residence | H11: =SUMIF($A$5:$A$54,G11,$C$5:$C$54)
A12: Primary Residence | B12: Council Rates | C12: 0 | D12: =C12*12 | G12: Medical | H12: =SUMIF($A$5:$A$54,G12,$C$5:$C$54)
A13: Primary Residence | B13: Water & Sewer | C13: 0 | D13: =C13*12 | G13: Housing | H13: =SUMIF($A$5:$A$54,G13,$C$5:$C$54)
A14: Primary Residence | B14: Body Corporate | C14: 0 | D14: =C14*12 | G14: Personal Care | H14: =SUMIF($A$5:$A$54,G14,$C$5:$C$54)
A15: Primary Residence | B15: Home Repairs | C15: 0 | D15: =C15*12 | G15: Recreation | H15: =SUMIF($A$5:$A$54,G15,$C$5:$C$54)
A16: Primary Residence | B16: Furnishings & Electrical | C16: 0 | D16: =C16*12 | G16: Communications | H16: =SUMIF($A$5:$A$54,G16,$C$5:$C$54)
... A18: Insurance | B18: Contents Insurance | C18: 0 | D18: =C18*12 | G18: Other | H18: =SUMIF($A$5:$A$54,G18,$C$5:$C$54)
A19: Insurance | B19: Health Insurance | C19: 0 | D19: =C19*12 | G19: TOTAL | H19: =SUM(H5:H18)
A20: Insurance | B20: Income Protection | C20: 0 | D20: =C20*12
A21: Insurance | B21: Life Insurance | C21: 0 | D21: =C21*12
A22: Insurance | B22: Vehicle Insurance | C22: 0 | D22: =C22*12
A23: Investment Property | B23: Rates, Utilities & Body Corporate | C23: 0 | D23: =C23*12
A24: Investment Property | B24: Repairs & Maintenance | C24: 0 | D24: =C24*12
A25: Investment Property | B25: Insurance | C25: 0 | D25: =C25*12
A26: Secondary Residence | B26: Rates, Utilities & Body Corporate | C26: 0 | D26: =C26*12
A27: Secondary Residence | B27: Repairs & Maintenance | C27: 0 | D27: =C27*12
A28: Secondary Residence | B28: Insurance | C28: 0 | D28: =C28*12
A29: Medical | B29: Medical & Health | C29: 0 | D29: =C29*12
A30: Medical | B30: Natural Therapies | C30: 0 | D30: =C30*12
A31: Housing | B31: Rent | C31: 0 | D31: =C31*12
... A54: Other | B54: Other Regular Expense | C54: 0 | D54: =C54*12
A55: TOTAL MONTHLY LIVING EXPENSES | C55: =SUM(C5:C54) | D55: =SUM(D5:D54)
A57: ENTERING AMOUNTS Enter the average monthly amount for each line. Convert weekly figures by multiplying by 52 and dividing by 12; convert annual figures by dividing by 12. Leave a line at zero where it does not apply — the category roll-up on the right updates automatically.

Sheet Client Form Output
A1: ='White Label Setup'!C6
A4: ='White Label Setup'!C8
A6: ='White Label Setup'!F6
A8: ='White Label Setup'!F7&" · Prepared by "&IF('White Label Setup'!F8="",""&'White Label Setup'!C6,'White Label Setup'!F8)&" · Version "&'White Label Setup'!F9
A10: PORTFOLIO SUMMARY Calculated from the fact find
A12: TOTAL ASSETS | C12: TOTAL DEBT | E12: NET POSITION | G12: MONTHLY EXPENSES
A13: ='Client Fact Find'!D50 | C13: ='Client Fact Find'!G50+'Client Fact Find'!F61 | E13: =A13-C13 | G13: ='Living Expenses'!C55
A16: PERSONAL DETAILS
A17: PRIMARY APPLICANT | E17: SECONDARY APPLICANT
A18: Full Name | C18: =TRIM('Client Fact Find'!C7&" "&'Client Fact Find'!C8&" "&'Client Fact Find'!C9) | E18: Full Name | G18: =TRIM('Client Fact Find'!H7&" "&'Client Fact Find'!H8&" "&'Client Fact Find'!H9)
A19: Date of Birth | C19: =IF('Client Fact Find'!C10="","",'Client Fact Find'!C10) | E19: Date of Birth | G19: =IF('Client Fact Find'!H10="","",'Client Fact Find'!H10)
A20: Mobile | C20: =IF('Client Fact Find'!C15="","",'Client Fact Find'!C15) | E20: Mobile | G20: =IF('Client Fact Find'!H15="","",'Client Fact Find'!H15)
A21: Email | C21: =IF('Client Fact Find'!C16="","",'Client Fact Find'!C16) | E21: Email | G21: =IF('Client Fact Find'!H16="","",'Client Fact Find'!H16)
A22: Current Address | C22: =IF('Client Fact Find'!C19="","",'Client Fact Find'!C19) | E22: Current Address | G22: =IF('Client Fact Find'!H19="","",'Client Fact Find'!H19)
A23: Living Situation | C23: =IF('Client Fact Find'!C20="","",'Client Fact Find'!C20) | E23: Living Situation | G23: =IF('Client Fact Find'!H20="","",'Client Fact Find'!H20)
A25: EMPLOYMENT & INCOME
A26: PRIMARY APPLICANT | E26: SECONDARY APPLICANT
A27: Employer / Business | C27: =IF('Client Fact Find'!C28="","",'Client Fact Find'!C28) | E27: Employer / Business | G27: =IF('Client Fact Find'!H28="","",'Client Fact Find'!H28)
A28: Role / Position | C28: =IF('Client Fact Find'!C29="","",'Client Fact Find'!C29) | E28: Role / Position | G28: =IF('Client Fact Find'!H29="","",'Client Fact Find'!H29)
A29: Employment Type | C29: =IF('Client Fact Find'!C27="","",'Client Fact Find'!C27) | E29: Employment Type | G29: =IF('Client Fact Find'!H27="","",'Client Fact Find'!H27)
A30: Start Date | C30: =IF('Client Fact Find'!C31="","",'Client Fact Find'!C31) | E30: Start Date | G30: =IF('Client Fact Find'!H31="","",'Client Fact Find'!H31)
A31: Total Annual Income | C31: =SUM('Client Fact Find'!C32:C36) | E31: Total Annual Income | G31: =SUM('Client Fact Find'!H32:H36)
A33: ASSETS, LIABILITIES & LIVING EXPENSES Roll-up — see the fact find for line detail
A34: Category | B34: Description | D34: Value / Balance | F34: Monthly | H34: Source
A35: Assets | B35: Total assets recorded in the fact find | D35: ='Client Fact Find'!D50 | H35: Client Fact Find
A36: Liabilities | B36: Secured loans plus other liabilities | D36: ='Client Fact Find'!G50+'Client Fact Find'!F61 | F36: ='Client Fact Find'!H50+'Client Fact Find'!G61 | H36: Client Fact Find
A37: Living expenses | B37: Monthly household expenditure | F37: ='Living Expenses'!C55 | H37: Living Expenses
A38: Net position | B38: Assets less liabilities | D38: =D35-D36 | H38: Calculated
A40: DECLARATION The information contained in this fact find has been provided for the purpose of assessing the client's financial position and coordinating with authorised finance and property professionals. It does not constitute credit assistance, financial product advice or legal advice. The client should verify all information before relying on the generated document.
A45: Client signature: __________________________________ | E45: Date: ____ / ____ / ______
A47: ='White Label Setup'!C10&" · "&'White Label Setup'!C11&" · "&'White Label Setup'!C12&" · "&'White Label Setup'!C6
A48: ='White Label Setup'!F13

Sheet Lists
A1: Title | B1: Gender | C1: MaritalStatus | D1: Residency | E1: LivingSituation | F1: EmploymentType | G1: Owner | H1: AssetType | I1: LiabilityType | J1: YesNo | K1: Frequency
A2: Mr | B2: Female | C2: Single | D2: Australian citizen | E2: Owned | F2: PAYG full time | G2: Applicant 1 | H2: Owner-occupied property | I2: Home loan | J2: Yes | K2: Weekly
A3: Mrs | B3: Male | C3: Married | D3: Permanent resident | E3: Mortgaged | F3: PAYG part time | G3: Applicant 2 | H3: Investment property | I3: Investment loan | J3: No | K3: Fortnightly
A4: Ms | B4: Non-binary | C4: De facto | D4: Temporary visa | E4: Renting | F4: PAYG casual | G4: Joint | H4: Vehicle | I4: Personal loan | K4: Monthly
A5: Miss | B5: Prefer not to say | C5: Separated | D5: New Zealand citizen | E5: Boarding | F5: Contract | G5: Other | H5: Savings / cash | I5: Car loan | K5: Quarterly
A6: Dr | B6: Other | C6: Divorced | D6: Non-resident | E6: Living with parents | F6: Self-employed | H6: Term deposit | I6: Credit card | K6: Annually
A7: Other | C7: Widowed | D7: Other | E7: Other | F7: Company director | H7: Shares / managed funds | I7: Store card
F8: Retired | H8: Superannuation | I8: Overdraft
F9: Home duties | H9: Business interest | I9: Buy now pay later
F10: Student | H10: Contents | I10: HECS / HELP
F11: Unemployed | H11: Other | I11: Tax debt
I12: Other
