Workbook

Sheet White Label Setup
A1: WHITE-LABEL CONFIGURATION
A4: Brand Field | B4: Editable Value | D4: Document Settings
A5: Organisation Name | B5: ABC Company | D5: Document Title | E5: Client Financial Position & Fact Find
A6: Trading Name / Division | D6: Confidentiality Label | E6: CONFIDENTIAL
A7: Tagline | B7: YOUR TRUSTED PROPERTY & FINANCE PARTNER | D7: Prepared By
A8: Primary Colour (Hex) | B8: #12345B | D8: Logo Placeholder | E8: Replace this area with your logo in Orixa
A9: Accent Colour (Hex) | B9: #C9A227 | D9: Version | E9: 1.0
A10: Website | B10: www.yourorganisation.com.au
A11: Email | B11: info@yourorganisation.com.au
A12: Phone | B12: (00) 0000 0000
A13: Business Address | B13: Insert business address
A15: IMPLEMENTATION NOTE
A16: This workbook is intentionally organisation-neutral. The Aurixa Systems Client Forms module can map each editable field to its database, apply the selected organisation's brand settings, and generate the downloadable 'Client Form Output' without displaying any external finance-partner branding.

Sheet Client Fact Find
A1: CLIENT FACT FIND
A3: ='White Label Setup'!B5&" | "&'White Label Setup'!E5 -> ABC Company | Client Financial Position & Fact Find
A5: APPLICANT 1 - PERSONAL DETAILS | F5: APPLICANT 2 - PERSONAL DETAILS
A6: Title | F6: Title
A7: First Name | F7: First Name
A8: Middle Name | F8: Middle Name
A9: Surname | F9: Surname
A10: Date of Birth | F10: Date of Birth
A11: Gender | F11: Gender
A12: Marital Status | F12: Marital Status
A13: Residency Status | F13: Residency Status
A14: Number of Dependants | F14: Number of Dependants
A15: Mobile | F15: Mobile
A16: Email | F16: Email
... A36: Other Taxable Income | F36: Other Taxable Income
A38: ASSETS
A39: Asset Type | B39: Description / Address | C39: Owner | D39: Current Value | E39: Rental / Other Income | F39: Financial Institution | G39: Loan Balance | H39: Monthly Repayment | I39: Interest Rate | J39: Maturity Date
A51: OTHER LIABILITIES
A52: Liability Type | B52: Lender | C52: Account / Description | D52: Owner | E52: Limit / Original Amount | F52: Current Balance | G52: Monthly Repayment | H52: Interest Rate | I52: Remaining Term | J52: Notes

Sheet Living Expenses
A1: MONTHLY LIVING EXPENSES
A4: Category | B4: Expense Item | C4: Monthly Amount | D4: Notes
A5: Childcare & Support | B5: Childcare | C5: 0
A6: Childcare & Support | B6: Child Maintenance | C6: 0
A7: Education | B7: Public School Costs | C7: 0
A8: Education | B8: Private School Costs | C8: 0
A9: Education | B9: Higher Education / Vocational Training | C9: 600
A10: Groceries | B10: Groceries | C10: 0
A11: Primary Residence | B11: Electricity & Gas | C11: 0
A12: Primary Residence | B12: Council Rates | C12: 0
A13: Primary Residence | B13: Water & Sewer | C13: 0
A14: Primary Residence | B14: Body Corporate | C14: 0
A15: Primary Residence | B15: Home Repairs | C15: 0
A16: Primary Residence | B16: Furnishings & Electrical | C16: 0
... A54: Other | B54: Other Regular Expense | C54: 0
A55: TOTAL MONTHLY LIVING EXPENSES | C55: =SUM(C5:C54) -> 600

Sheet Client Form Output
A1: ='White Label Setup'!B5 -> ABC Company
A5: ='White Label Setup'!B7 -> YOUR TRUSTED PROPERTY & FINANCE PARTNER
A7: CLIENT FINANCIAL POSITION & FACT FIND
A10: PORTFOLIO SUMMARY
A12: TOTAL ASSETS | C12: TOTAL DEBT | E12: NET POSITION | G12: MONTHLY EXPENSES
A14: =SUM('Client Fact Find'!D40:D49) -> 0 | C14: =SUM('Client Fact Find'!G40:G49)+SUM('Client Fact Find'!F53:F60) -> 0 | E14: =A14-C14 -> 0 | G14: ='Living Expenses'!C55 -> 600
A18: PERSONAL DETAILS
A20: PRIMARY APPLICANT | E20: SECONDARY APPLICANT
A21: Full Name | C21: =TRIM('Client Fact Find'!C7&" "&'Client Fact Find'!C8&" "&'Client Fact Find'!C9) | E21: Full Name | G21: =TRIM('Client Fact Find'!H7&" "&'Client Fact Find'!H8&" "&'Client Fact Find'!H9)
A22: Date of Birth | C22: =IF('Client Fact Find'!C10="","",'Client Fact Find'!C10) | E22: Date of Birth | G22: =IF('Client Fact Find'!H10="","",'Client Fact Find'!H10)
A23: Mobile | C23: =IF('Client Fact Find'!C15="","",'Client Fact Find'!C15) | E23: Mobile | G23: =IF('Client Fact Find'!H15="","",'Client Fact Find'!H15)
A24: Email | C24: =IF('Client Fact Find'!C16="","",'Client Fact Find'!C16) | E24: Email | G24: =IF('Client Fact Find'!H16="","",'Client Fact Find'!H16)
A25: Current Address | C25: =IF('Client Fact Find'!C19="","",'Client Fact Find'!C19) | E25: Current Address | G25: =IF('Client Fact Find'!H19="","",'Client Fact Find'!H19)
A26: Living Situation | C26: =IF('Client Fact Find'!C20="","",'Client Fact Find'!C20) | E26: Living Situation | G26: =IF('Client Fact Find'!H20="","",'Client Fact Find'!H20)
A29: EMPLOYMENT & INCOME
A31: PRIMARY APPLICANT | E31: SECONDARY APPLICANT
A32: Employer / Business | C32: =IF('Client Fact Find'!C28="","",'Client Fact Find'!C28) | E32: Employer / Business | G32: =IF('Client Fact Find'!H28="","",'Client Fact Find'!H28)
A33: Role / Position | C33: =IF('Client Fact Find'!C29="","",'Client Fact Find'!C29) | E33: Role / Position | G33: =IF('Client Fact Find'!H29="","",'Client Fact Find'!H29)
A34: Employment Type | C34: =IF('Client Fact Find'!C27="","",'Client Fact Find'!C27) | E34: Employment Type | G34: =IF('Client Fact Find'!H27="","",'Client Fact Find'!H27)
A35: Start Date | C35: =IF('Client Fact Find'!C31="","",'Client Fact Find'!C31) | E35: Start Date | G35: =IF('Client Fact Find'!H31="","",'Client Fact Find'!H31)
A36: Total Annual Income | C36: =SUM('Client Fact Find'!C32:C36) -> 0 | E36: Total Annual Income | G36: =SUM('Client Fact Find'!H32:H36) -> 0
A40: ASSETS, LIABILITIES & LIVING EXPENSES
A42: Category | B42: Description | C42: Owner | D42: Value / Balance | E42: Income | F42: Repayment | G42: Rate | H42: Notes
A43: Assets | B43: Refer to Client Fact Find | D43: =A14 -> 0
A44: Liabilities | B44: Refer to Client Fact Find | D44: =C14 -> 0
A45: Living Expenses | B45: Monthly household expenditure | D45: 0
A46: Net Position | B46: Assets less liabilities | D46: =E14 -> 0
A50: DECLARATION
A51: The information contained in this fact find has been provided for the purpose of assessing the client's financial position and coordinating with authorised finance and property professionals. It does not constitute credit assistance, financial product advice or legal advice. The client should verify all information before relying on the generated document.
A55: Client Signature: __________________________ | E55: Date: ____ / ____ / ______
A58: ='White Label Setup'!B11&" | "&'White Label Setup'!B12&" | "&'White Label Setup'!B13 -> info@yourorganisation.com.au | (00) 0000 0000 | Insert business address
